demux8to1/simple.v
module mux8to1_16bit(in,sel,out1,out2,out3,out4,out5,out6,out7,out8);
parameter width = 16;
input [width-1:0]in;
input [2:0] sel;
output [width-1:0] out1,out2,out3,out4,out5,out6,out7,out8;
reg [width-1:0] out1,out2,out3,out4,out5,out6,out7,out8;

always @ (in or sel)
begin
    if(sel[2:0]=='b000)
    begin
    out1[width-1:0] = in[width-1:0];
    out2[width-1:0]='b0000000000000000;
    out3[width-1:0]='b0000000000000000;
    out4[width-1:0]='b0000000000000000;
    out5[width-1:0]='b0000000000000000;
    out6[width-1:0]='b0000000000000000;
    out7[width-1:0]='b0000000000000000;
    out8[width-1:0]='b0000000000000000;
    end
    else if(sel[2:0]=='b001)
    begin
    out2[width-1:0] = in[width-1:0];
    out1[width-1:0]='b0000000000000000;
    out3[width-1:0]='b0000000000000000;
    out4[width-1:0]='b0000000000000000;
    out5[width-1:0]='b0000000000000000;
    out6[width-1:0]='b0000000000000000;
    out7[width-1:0]='b0000000000000000;
    out8[width-1:0]='b0000000000000000;
    end
    else if(sel[2:0]=='b010)
    begin
    out3[width-1:0] = in[width-1:0];
    out2[width-1:0]='b0000000000000000;
    out1[width-1:0]='b0000000000000000;
    out4[width-1:0]='b0000000000000000;
    out5[width-1:0]='b0000000000000000;
    out6[width-1:0]='b0000000000000000;
    out7[width-1:0]='b0000000000000000;
    out8[width-1:0]='b0000000000000000;
    end
    else if(sel[2:0]=='b011)
    begin
    out4[width-1:0] = in[width-1:0];
    out2[width-1:0]='b0000000000000000;
    out3[width-1:0]='b0000000000000000;
    out1[width-1:0]='b0000000000000000;
    out5[width-1:0]='b0000000000000000;
    out6[width-1:0]='b0000000000000000;
    out7[width-1:0]='b0000000000000000;
    out8[width-1:0]='b0000000000000000;
    end
    else if(sel[2:0]=='b100)
    begin
    out5[width-1:0] = in[width-1:0];
    out2[width-1:0]='b0000000000000000;
    out3[width-1:0]='b0000000000000000;
    out4[width-1:0]='b0000000000000000;
    out1[width-1:0]='b0000000000000000;
    out6[width-1:0]='b0000000000000000;
    out7[width-1:0]='b0000000000000000;
    out8[width-1:0]='b0000000000000000;
    end
    else if(sel[2:0]=='b101)
    begin
    out6[width-1:0] = in[width-1:0];
    out2[width-1:0]='b0000000000000000;
    out3[width-1:0]='b0000000000000000;
    out4[width-1:0]='b0000000000000000;
    out5[width-1:0]='b0000000000000000;
    out1[width-1:0]='b0000000000000000;
    out7[width-1:0]='b0000000000000000;
    out8[width-1:0]='b0000000000000000;
    end
    else if(sel[2:0]=='b110)
    begin
    out7[width-1:0] = in[width-1:0];
    out2[width-1:0]='b0000000000000000;
    out3[width-1:0]='b0000000000000000;
    out4[width-1:0]='b0000000000000000;
    out5[width-1:0]='b0000000000000000;
    out6[width-1:0]='b0000000000000000;
    out1[width-1:0]='b0000000000000000;
    out8[width-1:0]='b0000000000000000;
    end
    else if(sel[2:0]=='b111)
    begin
    out8[width-1:0] = in[width-1:0];
    out2[width-1:0]='b0000000000000000;
    out3[width-1:0]='b0000000000000000;
    out4[width-1:0]='b0000000000000000;
    out5[width-1:0]='b0000000000000000;
    out6[width-1:0]='b0000000000000000;
    out7[width-1:0]='b0000000000000000;
    out1[width-1:0]='b0000000000000000;
    end
end 

endmodule

demux8to1/testbench_simple.v
`timescale 1ns/10ps
module testbench_simple;
parameter width = 16;
reg [width-1:0] in;
reg [2:0] sel;
wire [width-1:0] out1,out2,out3,out4,out5,out6,out7,out8;
mux8to1_16bit mymux(in,sel,out1,out2,out3,out4,out5,out6,out7,out8);
initial
begin
	$dumpfile("testbench_simple.vcd");//the name of the .vcd file should be as the same as the testbecnh file
	$dumpvars(0,testbench_simple);
	in='b1111111111111111;
	sel='b000;
	#1;
	sel='b001;
	#1;
	sel='b010;
	#1;
	sel='b011;
	#1;
	sel='b100;
	#1;
	sel='b101;
	#1;
	sel='b110;
	#1;
	sel='b111;
	#1;
	sel='b111;
        $finish;
end
endmodule

demux8to1/testbench_simple.vcd
$date
	Mon Sep 19 01:03:23 2016
$end
$version
	Icarus Verilog
$end
$timescale
	10ps
$end
$scope module testbench_simple $end
$var wire 16 ! out8 [15:0] $end
$var wire 16 " out7 [15:0] $end
$var wire 16 # out6 [15:0] $end
$var wire 16 $ out5 [15:0] $end
$var wire 16 % out4 [15:0] $end
$var wire 16 & out3 [15:0] $end
$var wire 16 ' out2 [15:0] $end
$var wire 16 ( out1 [15:0] $end
$var reg 16 ) in [15:0] $end
$var reg 3 * sel [2:0] $end
$scope module mymux $end
$var wire 16 + in [15:0] $end
$var wire 3 , sel [2:0] $end
$var reg 16 - out1 [15:0] $end
$var reg 16 . out2 [15:0] $end
$var reg 16 / out3 [15:0] $end
$var reg 16 0 out4 [15:0] $end
$var reg 16 1 out5 [15:0] $end
$var reg 16 2 out6 [15:0] $end
$var reg 16 3 out7 [15:0] $end
$var reg 16 4 out8 [15:0] $end
$upscope $end
$upscope $end
$enddefinitions $end
#0
$dumpvars
b0 4
b0 3
b0 2
b0 1
b0 0
b0 /
b0 .
b1111111111111111 -
b0 ,
b1111111111111111 +
b0 *
b1111111111111111 )
b1111111111111111 (
b0 '
b0 &
b0 %
b0 $
b0 #
b0 "
b0 !
$end
#100
b0 (
b0 -
b1111111111111111 '
b1111111111111111 .
b1 *
b1 ,
#200
b0 '
b0 .
b1111111111111111 &
b1111111111111111 /
b10 *
b10 ,
#300
b0 &
b0 /
b1111111111111111 %
b1111111111111111 0
b11 *
b11 ,
#400
b0 %
b0 0
b1111111111111111 $
b1111111111111111 1
b100 *
b100 ,
#500
b0 $
b0 1
b1111111111111111 #
b1111111111111111 2
b101 *
b101 ,
#600
b0 #
b0 2
b1111111111111111 "
b1111111111111111 3
b110 *
b110 ,
#700
b0 "
b0 3
b1111111111111111 !
b1111111111111111 4
b111 *
b111 ,
