Mux2to1/simple.v
module mux2to1(in0,in1,s,out);
input in0,in1,s;
output out;
reg out;
always @ (in0 or in1 or s)
begin
    if(s == 0)
    begin
    	out= in0;
    end
    else
    begin
	out = in1;
    end
end 

endmodule

Mux2to1/testbench_simple.v

`timescale 1ns/10ps
module testbench_simple;
reg in0,in1,s;
wire out;
mux2to1 mymux(in0,in1,s,out);
initial
begin
	$dumpfile("testbench_simple.vcd");//the name of the .vcd file should be as the same as the testbecnh file
	$dumpvars(0,testbench_simple);
	in0 = 0;
	in1 = 0;
	s=0;
	#1;
	in0 = 0;
	in1 = 0;
	s=1;
	#1;
	in0 = 0;
	in1 = 1;
	s=0;
	#1;
	in0 = 0;
	in1 = 1;
	s=1;
	#1
	in0 = 1;
	in1 = 0;
	s=0;
	#1;
	in0 = 1;
	in1 = 0;
	s=1;
	#1;
	in0 = 1;
	in1 = 1;
	s=0;
	#1;
	in0 = 1;
	in1 = 1;
	s=1;
	#1;
	in0 = 0;
	in1 = 0;
	s=0;
        $finish;
end
endmodule

Mux2to1/testbench_simple.vcd
$date
	Sun Sep 18 09:49:31 2016
$end
$version
	Icarus Verilog
$end
$timescale
	10ps
$end
$scope module testbench_simple $end
$var wire 1 ! out $end
$var reg 1 " in0 $end
$var reg 1 # in1 $end
$var reg 1 $ s $end
$scope module mymux $end
$var wire 1 " in0 $end
$var wire 1 # in1 $end
$var wire 1 $ s $end
$var reg 1 ! out $end
$upscope $end
$upscope $end
$enddefinitions $end
#0
$dumpvars
0$
0#
0"
0!
$end
#100
1$
#200
0$
1#
#300
1!
1$
#400
0$
0#
1"
#500
0!
1$
#600
1!
0$
1#
#700
1$
#800
0!
0$
0#
0"
