mux8to1_16bit/simple.v
module mux8to1_16bit(in0,in1,in2,in3,in4,in5,in6,in7,sel,out);
parameter width = 16;
input [width-1:0]in0,in1,in2,in3,in4,in5,in6,in7;
input [2:0] sel;
output [width-1:0] out;
reg [width-1:0] out;

always @ (in0 or in1 or in2 or in3 or in4 or in5 or in6 or in7 or sel)
begin
    if(sel[2:0]=='b000)
    begin
    out[width-1:0] = in0[width-1:0];
    end
    else if(sel[2:0]=='b001)
    begin
    out[width-1:0] = in1[width-1:0];
    end
    else if(sel[2:0]=='b010)
    begin
    out[width-1:0] = in2[width-1:0];
    end
    else if(sel[2:0]=='b011)
    begin
    out[width-1:0] = in3[width-1:0];
    end
    else if(sel[2:0]=='b100)
    begin
    out[width-1:0] = in4[width-1:0];
    end
    else if(sel[2:0]=='b101)
    begin
    out[width-1:0] = in5[width-1:0];
    end
    else if(sel[2:0]=='b110)
    begin
    out[width-1:0] = in6[width-1:0];
    end
    else if(sel[2:0]=='b111)
    begin
    out[width-1:0] = in7[width-1:0];
    end
end 

endmodule

mux8to1_16bit/testbench_simple.v
`timescale 1ns/10ps
module testbench_simple;
parameter width = 16;
reg [width-1:0] in0,in1,in2,in3,in4,in5,in6,in7;
reg [2:0] sel;
wire [width-1:0] out;
mux8to1_16bit mymux(in0,in1,in2,in3,in4,in5,in6,in7,sel,out);
initial
begin
	$dumpfile("testbench_simple.vcd");//the name of the .vcd file should be as the same as the testbecnh file
	$dumpvars(0,testbench_simple);
	in0='b1111111111111111;
	in1='b0000000000000000;
	in2='b1111111000000000;
	in3='b0000000111111111;
	in4='b0001000111111111;
	in5='b0000000111110111;
	in6='b0100000111110111;
	in7='b1100000111111111;
	sel='b000;
	#1;
	in0='b1111111111111111;
	in1='b0000000000000000;
	in2='b1111111000000000;
	in3='b0000000111111111;
	in4='b0001000111111111;
	in5='b0000000111110111;
	in6='b0100000111110111;
	in7='b1100000111111111;
	sel='b001;
	#1;
	in0='b1111111111111111;
	in1='b0000000000000000;
	in2='b1111111000000000;
	in3='b0000000111111111;
	in4='b0001000111111111;
	in5='b0000000111110111;
	in6='b0100000111110111;
	in7='b1100000111111111;
	sel='b010;
	#1;
	in0='b1111111111111111;
	in1='b0000000000000000;
	in2='b1111111000000000;
	in3='b0000000111111111;
	in4='b0001000111111111;
	in5='b0000000111110111;
	in6='b0100000111110111;
	in7='b1100000111111111;
	sel='b011;
	#1;
	in0='b1111111111111111;
	in1='b0000000000000000;
	in2='b1111111000000000;
	in3='b0000000111111111;
	in4='b0001000111111111;
	in5='b0000000111110111;
	in6='b0100000111110111;
	in7='b1100000111111111;
	sel='b100;
	#1;
	in0='b1111111111111111;
	in1='b0000000000000000;
	in2='b1111111000000000;
	in3='b0000000111111111;
	in4='b0001000111111111;
	in5='b0000000111110111;
	in6='b0100000111110111;
	in7='b1100000111111111;
	sel='b101;
	#1;
	in0='b1111111111111111;
	in1='b0000000000000000;
	in2='b1111111000000000;
	in3='b0000000111111111;
	in4='b0001000111111111;
	in5='b0000000111110111;
	in6='b0100000111110111;
	in7='b1100000111111111;
	sel='b110;
	#1;
	in0='b1111111111111111;
	in1='b0000000000000000;
	in2='b1111111000000000;
	in3='b0000000111111111;
	in4='b0001000111111111;
	in5='b0000000111110111;
	in6='b0100000111110111;
	in7='b1100000111111111;
	sel='b111;
	#1;
	in0='b1111111111111111;
	in1='b0000000000000000;
	in2='b1111111000000000;
	in3='b0000000111111111;
	in4='b0001000111111111;
	in5='b0000000111110111;
	in6='b0100000111110111;
	in7='b1100000111111111;
	sel='b111;
        $finish;
end
endmodule

mux8to1_16bit/testbench_simple.vcd
$date
	Mon Sep 19 00:23:39 2016
$end
$version
	Icarus Verilog
$end
$timescale
	10ps
$end
$scope module testbench_simple $end
$var wire 16 ! out [15:0] $end
$var reg 16 " in0 [15:0] $end
$var reg 16 # in1 [15:0] $end
$var reg 16 $ in2 [15:0] $end
$var reg 16 % in3 [15:0] $end
$var reg 16 & in4 [15:0] $end
$var reg 16 ' in5 [15:0] $end
$var reg 16 ( in6 [15:0] $end
$var reg 16 ) in7 [15:0] $end
$var reg 3 * sel [2:0] $end
$scope module mymux $end
$var wire 16 + in0 [15:0] $end
$var wire 16 , in1 [15:0] $end
$var wire 16 - in2 [15:0] $end
$var wire 16 . in3 [15:0] $end
$var wire 16 / in4 [15:0] $end
$var wire 16 0 in5 [15:0] $end
$var wire 16 1 in6 [15:0] $end
$var wire 16 2 in7 [15:0] $end
$var wire 3 3 sel [2:0] $end
$var reg 16 4 out [15:0] $end
$upscope $end
$upscope $end
$enddefinitions $end
#0
$dumpvars
b1111111111111111 4
b0 3
b1100000111111111 2
b100000111110111 1
b111110111 0
b1000111111111 /
b111111111 .
b1111111000000000 -
b0 ,
b1111111111111111 +
b0 *
b1100000111111111 )
b100000111110111 (
b111110111 '
b1000111111111 &
b111111111 %
b1111111000000000 $
b0 #
b1111111111111111 "
b1111111111111111 !
$end
#100
b0 !
b0 4
b1 *
b1 3
#200
b1111111000000000 !
b1111111000000000 4
b10 *
b10 3
#300
b111111111 !
b111111111 4
b11 *
b11 3
#400
b1000111111111 !
b1000111111111 4
b100 *
b100 3
#500
b111110111 !
b111110111 4
b101 *
b101 3
#600
b100000111110111 !
b100000111110111 4
b110 *
b110 3
#700
b1100000111111111 !
b1100000111111111 4
b111 *
b111 3
